labelroi/__init__.py
labelroi/labelroi.py
labelroi-0.1.0.dist-info/WHEEL
labelroi-0.1.0.dist-info/entry_points.txt
labelroi-0.1.0.dist-info/METADATA
labelroi-0.1.0.dist-info/RECORD
