Metadata-Version: 2.3
Name: labelroi
Version: 0.1.0
Summary: Add your description here
Author: Talmo Pereira
Author-email: Talmo Pereira <talmo@talmolab.org>
Requires-Dist: matplotlib>=3.10.5
Requires-Dist: numpy>=2.3.2
Requires-Dist: pyqt5>=5.15.11
Requires-Dist: pyyaml>=6.0.2
Requires-Dist: qtpy>=2.4.3
Requires-Dist: shapely>=2.1.1
Requires-Dist: sleap-io>=0.4.1
Requires-Python: >=3.11
